PFFRA.py
PFFRA-1.0.2.dist-info/LICENSE
PFFRA-1.0.2.dist-info/METADATA
PFFRA-1.0.2.dist-info/WHEEL
PFFRA-1.0.2.dist-info/top_level.txt
PFFRA-1.0.2.dist-info/RECORD
